Metadata-Version: 2.1
Name: NumIM04
Version: 0.0.1
Summary: Numerical integration using methods like: Trapezoidal method, Simpson rule, Newton cotes method and Compound trapezoidal method 
Home-page: 
Author: Emmanuel Martínez
Author-email: 
License: MIT
Keywords: numerical integration
Classifier: Development Status :: 5 - Production/Stable
Classifier: Intended Audience :: Education
Classifier: Operating System :: Microsoft :: Windows :: Windows 10
Classifier: License :: OSI Approved :: MIT License
Classifier: Programming Language :: Python :: 3
License-File: LICENCE.txt
